pytest_cloudflare_worker/__init__.py
pytest_cloudflare_worker/inspect.py
pytest_cloudflare_worker/main.py
pytest_cloudflare_worker/plugin.py
pytest_cloudflare_worker/version.py
pytest_cloudflare_worker-0.0.4.dist-info/LICENSE
pytest_cloudflare_worker-0.0.4.dist-info/METADATA
pytest_cloudflare_worker-0.0.4.dist-info/WHEEL
pytest_cloudflare_worker-0.0.4.dist-info/entry_points.txt
pytest_cloudflare_worker-0.0.4.dist-info/top_level.txt
pytest_cloudflare_worker-0.0.4.dist-info/zip-safe
pytest_cloudflare_worker-0.0.4.dist-info/RECORD
