Metadata-Version: 2.1
Name: pytest-cloudflare-worker
Version: 0.0.4
Summary: pytest plugin for testing cloudflare workers
Home-page: https://github.com/samuelcolvin/pytest-cloudflare-worker
Author: Samuel Colvin
Author-email: s@muelcolvin.com
License: MIT
Platform: UNKNOWN
Classifier: Development Status :: 4 - Beta
Classifier: Programming Language :: Python
Classifier: Programming Language :: Python :: 3
Classifier: Programming Language :: Python :: 3 :: Only
Classifier: Programming Language :: Python :: 3.8
Classifier: Intended Audience :: Developers
Classifier: Intended Audience :: Information Technology
Classifier: Intended Audience :: System Administrators
Classifier: License :: OSI Approved :: MIT License
Classifier: Operating System :: Unix
Classifier: Operating System :: POSIX :: Linux
Classifier: Environment :: MacOS X
Classifier: Topic :: Internet
Classifier: Framework :: Pytest
Classifier: Framework :: AsyncIO
Requires-Python: >=3.8
Requires-Dist: requests (>=2.24.0)
Requires-Dist: websockets (>=8.1)
Requires-Dist: pytest (>=6.0.0)
Requires-Dist: toml (>=0.10.1)
